pcdsdaq/__init__.py
pcdsdaq/_version.py
pcdsdaq/ami.py
pcdsdaq/exceptions.py
pcdsdaq/ext_scripts.py
pcdsdaq/plans.py
pcdsdaq/preprocessors.py
pcdsdaq/scan_vars.py
pcdsdaq/version.py
pcdsdaq/daq/__init__.py
pcdsdaq/daq/interface.py
pcdsdaq/daq/lcls1.py
pcdsdaq/daq/lcls2.py
pcdsdaq/daq/original.py
pcdsdaq/sim/__init__.py
pcdsdaq/sim/pyami.py
pcdsdaq/sim/pydaq.py
pcdsdaq/tests/__init__.py
pcdsdaq/tests/conftest.py
pcdsdaq/tests/test_ami.py
pcdsdaq/tests/test_daq_lcls2.py
pcdsdaq/tests/test_daq_original.py
pcdsdaq/tests/test_ext_scripts.py
pcdsdaq/tests/test_preprocessors.py
pcdsdaq/tests/test_scan_vars.py
pcdsdaq-2.4.5.data/scripts/pcdsdaq_lib_setup
pcdsdaq-2.4.5.dist-info/AUTHORS.rst
pcdsdaq-2.4.5.dist-info/LICENSE.md
pcdsdaq-2.4.5.dist-info/METADATA
pcdsdaq-2.4.5.dist-info/WHEEL
pcdsdaq-2.4.5.dist-info/top_level.txt
pcdsdaq-2.4.5.dist-info/RECORD
